MANIFEST.in
README.rst
bootstrap.py
buildout.cfg
plone.cfg
setup.cfg
setup.py
docs/HISTORY.txt
docs/INSTALL.txt
docs/LICENSE.GPL
docs/LICENSE.txt
tutorate/__init__.py
tutorate.contenttypes.egg-info/PKG-INFO
tutorate.contenttypes.egg-info/SOURCES.txt
tutorate.contenttypes.egg-info/dependency_links.txt
tutorate.contenttypes.egg-info/entry_points.txt
tutorate.contenttypes.egg-info/namespace_packages.txt
tutorate.contenttypes.egg-info/not-zip-safe
tutorate.contenttypes.egg-info/paster_plugins.txt
tutorate.contenttypes.egg-info/requires.txt
tutorate.contenttypes.egg-info/top_level.txt
tutorate/contenttypes/.DS_Store
tutorate/contenttypes/INTEGRATION.txt
tutorate/contenttypes/Session.txt
tutorate/contenttypes/__init__.py
tutorate/contenttypes/configure.zcml
tutorate/contenttypes/session.py
tutorate/contenttypes/session.xml
tutorate/contenttypes/tests.py
tutorate/contenttypes/locales/README.txt
tutorate/contenttypes/models/session.xml
tutorate/contenttypes/profiles/.DS_Store
tutorate/contenttypes/profiles/default/.DS_Store
tutorate/contenttypes/profiles/default/metadata.xml
tutorate/contenttypes/profiles/default/registry.xml
tutorate/contenttypes/profiles/default/types.xml
tutorate/contenttypes/profiles/default/types/Folder.xml
tutorate/contenttypes/profiles/default/types/tutorate.contenttypes.session.xml
tutorate/contenttypes/resources/README.txt
tutorate/contenttypes/resources/session_icon.png
tutorate/contenttypes/session_templates/.DS_Store
tutorate/contenttypes/session_templates/sessionlisting.pt
tutorate/contenttypes/session_templates/view.pt