Metadata-Version: 1.1
Name: tutorate.contenttypes
Version: 1.0.7.3.1a
Summary: tutorate.contenttypes
Home-page: http://github.com/pigeonflight/tutorate.contenttypes
Author: David Bain
Author-email: pigeonflight@gmail.com
License: GPL
Keywords: session,training
Platform: UNKNOWN
Classifier: Framework :: Plone
Classifier: Programming Language :: Python
Classifier: Topic :: Software Development :: Libraries :: Python Modules
